python_githooks/__init__.py
python_githooks/__main__.py
python_githooks/constants.py
python_githooks/helpers.py
py_githooks-1.1.1.dist-info/LICENSE
py_githooks-1.1.1.dist-info/METADATA
py_githooks-1.1.1.dist-info/WHEEL
py_githooks-1.1.1.dist-info/entry_points.txt
py_githooks-1.1.1.dist-info/top_level.txt
py_githooks-1.1.1.dist-info/RECORD
