Metadata-Version: 2.1
Name: py-githooks
Version: 1.1.1
Summary: Create git hooks with ease using a simple configuration file in a git project
Home-page: https://github.com/iamogbz/python-githooks
Author: Emmanuel Ogbizi-Ugbe
Author-email: iamogbz+pygithooks@gmail.com
License: MIT
Platform: UNKNOWN
Classifier: License :: OSI Approved :: MIT License
Classifier: Programming Language :: Python :: 3
Classifier: Intended Audience :: Developers
Classifier: Topic :: Software Development
License-File: LICENSE
Requires-Dist: configparser
